samecode/__init__.py
samecode/chunking.py
samecode/halohash.py
samecode-0.5.1.dist-info/AUTHORS.rst
samecode-0.5.1.dist-info/CHANGELOG.rst
samecode-0.5.1.dist-info/CODE_OF_CONDUCT.rst
samecode-0.5.1.dist-info/METADATA
samecode-0.5.1.dist-info/NOTICE
samecode-0.5.1.dist-info/WHEEL
samecode-0.5.1.dist-info/apache-2.0.LICENSE
samecode-0.5.1.dist-info/top_level.txt
samecode-0.5.1.dist-info/RECORD
